fbviz/__init__.py
fbviz/understat.py
fbviz-0.0.1.dist-info/LICENSE
fbviz-0.0.1.dist-info/METADATA
fbviz-0.0.1.dist-info/WHEEL
fbviz-0.0.1.dist-info/top_level.txt
fbviz-0.0.1.dist-info/RECORD
